cansina/__init__.py
cansina/main.py
cansina/core/__init__.py
cansina/core/dbmanager.py
cansina/core/payload.py
cansina/core/printer.py
cansina/core/resumer.py
cansina/core/task.py
cansina/core/viewer.py
cansina/core/visitor.py
cansina/plugins/__init__.py
cansina/plugins/crawler.py
cansina/plugins/inspector.py
cansina/plugins/robots.py
cansina/utils/__init__.py
cansina/utils/misc.py
cansina/utils/ua.txt
cansina/utils/viewer.py
cansina-0.9.dist-info/LICENSE
cansina-0.9.dist-info/METADATA
cansina-0.9.dist-info/WHEEL
cansina-0.9.dist-info/entry_points.txt
cansina-0.9.dist-info/top_level.txt
cansina-0.9.dist-info/RECORD
