Metadata-Version: 2.1
Name: cansina
Version: 0.9
Summary: Web Content Discovery Tool
Home-page: https://github.com/deibit/cansina
Author: David Garcia
Author-email: daganu@gmail.com
Keywords: pentesting,cybersecurity,websecurity
License-File: LICENSE
Requires-Dist: requests
Requires-Dist: asciitree
